dict_from_xml/__init__.py
dict_from_xml/config.py
dict_from_xml-0.1.0.dist-info/LICENSE
dict_from_xml-0.1.0.dist-info/METADATA
dict_from_xml-0.1.0.dist-info/WHEEL
dict_from_xml-0.1.0.dist-info/RECORD
