Metadata-Version: 2.3
Name: dict_from_xml
Version: 0.1.0
Summary: This package converts xml files and xml strings to python dictionary objects.
License: [MIT]
Author: kkerber
Author-email: thekkerber@gmail.com
Requires-Python: >=3.10
Classifier: License :: Other/Proprietary License
Classifier: Programming Language :: Python :: 3
Classifier: Programming Language :: Python :: 3.10
Classifier: Programming Language :: Python :: 3.11
Classifier: Programming Language :: Python :: 3.12
Classifier: Programming Language :: Python :: 3.13
Requires-Dist: pytest (>=8.3.4,<9.0.0)
